{
  "comments": [
    {
      "date": "13 March 2019 11:15",
      "html": "There is the ONS at September 23 - 25, 2019 in Belgium this year : ) ... www.packetflow.co.uk",
      "id": "7352556841626249110",
      "image": "https://lh3.googleusercontent.com/zFdxGE77vvD2w5xHy6jkVuElKv-U9_9qLkRYK8OnbDeJPtjSZ82UPq5w6hJ-SA=s35",
      "name": "Unknown",
      "profile": "https://www.blogger.com/profile/12167799894831585282",
      "pub": "2019-03-13T11:15:45.301+01:00",
      "ref": "5266329410008570799",
      "type": "comment"
    },
    {
      "date": "13 March 2019 12:00",
      "html": "Small plug, I hope Ivan doesn&#39;t mind: we just started a new non-profit foundation to help and support operator groups to connect and to exchange experiences: https://nogalliance.org/. If you have any ideas on how to improve cooperation or want help organising a community please let us know!",
      "id": "3387942559809209629",
      "image": "https://4.bp.blogspot.com/-JXMUyJFF5iY/UkmoOMGUIVI/AAAAAAAAAGk/6jDTL3tcsI4/s32/1240469_10202242095038376_1044617343_n.jpg",
      "name": "Sander Steffann",
      "profile": "https://www.blogger.com/profile/17446363221396052047",
      "pub": "2019-03-13T12:00:26.364+01:00",
      "ref": "5266329410008570799",
      "type": "comment"
    },
    {
      "date": "14 March 2019 10:20",
      "html": "There is an ISP go-kart competition held in Holland each year. It originated from the Dutch/NLNOG group and thus its origins are ISP focussed, but nevertheless there seems to be a large enterprise IT component in there. Check: https://www.isp-kartcompetitie.nl/",
      "id": "1857201267961807163",
      "image": "https://lh3.googleusercontent.com/zFdxGE77vvD2w5xHy6jkVuElKv-U9_9qLkRYK8OnbDeJPtjSZ82UPq5w6hJ-SA=s35",
      "name": "Nils Kolstein",
      "profile": "https://www.blogger.com/profile/14632700309380669759",
      "pub": "2019-03-14T10:20:21.866+01:00",
      "ref": "5266329410008570799",
      "type": "comment"
    },
    {
      "date": "14 March 2019 12:59",
      "html": "for Germany there is DENOG (www.denog.de). It will be held in Hamburg in November this year. It&#39;s about 200 people. Its the meeting of the people haging out in IRCnet #denog<br />DKNOG is just taking place today and tomorrow in Kopenhagen and is also about 200 atendees. <br />When you are from an ISP go ahead and attend a RIPE meeting which is heald twice a year at different locations.",
      "id": "3406474359871909807",
      "image": "https://lh3.googleusercontent.com/zFdxGE77vvD2w5xHy6jkVuElKv-U9_9qLkRYK8OnbDeJPtjSZ82UPq5w6hJ-SA=s35",
      "name": "Unknown",
      "profile": "https://www.blogger.com/profile/03370697842771988340",
      "pub": "2019-03-14T12:59:43.798+01:00",
      "ref": "5266329410008570799",
      "type": "comment"
    },
    {
      "date": "14 March 2019 17:26",
      "html": "Hey mate, we&#39;ve been trying to get you to iNOG for some time, hint hint, nudge, nudge... with 100+ ppl every 2-3 months with speakers like Jason Edelman, Jose Liste, Laura Nolan etc at the last one alone, https://inog.net has had a wide range of FAANGs and focuses on all things related to networking. We also record all videos and there is now somewhat of a back catalog https://youtube.com/inognet Perhaps ask around your peers and see if they know iNOG :)  ",
      "id": "572168175811912073",
      "image": "https://4.bp.blogspot.com/-xQY4JttGiCw/W7XXHXiTEKI/AAAAAAAABpU/FbhLqq15knswnPBkwnPL2ig37sbxpLlhACK4BGAYYCw/s32/linked_in_donal_profile.png",
      "name": "Donal",
      "profile": "https://www.blogger.com/profile/13772533723547791668",
      "pub": "2019-03-14T17:26:11.677+01:00",
      "ref": "5266329410008570799",
      "type": "comment"
    },
    {
      "date": "19 March 2019 23:06",
      "html": "ONS seems promising but unfortunately pricey. More technical and less political than SDN NFV Congress. Some bits of OpenStack Summit, Kubecon/Cloudnativecon are worth looking into.",
      "id": "9060552554930957487",
      "image": "https://lh3.googleusercontent.com/zFdxGE77vvD2w5xHy6jkVuElKv-U9_9qLkRYK8OnbDeJPtjSZ82UPq5w6hJ-SA=s35",
      "name": "wchukov",
      "profile": "https://www.blogger.com/profile/10733884934786074428",
      "pub": "2019-03-19T23:06:34.360+01:00",
      "ref": "5266329410008570799",
      "type": "comment"
    }
  ],
  "count": 6,
  "id": "5266329410008570799",
  "type": "post",
  "url": "2019/03/networking-events-in-europe.html"
}