{
   "comments": [
      {
         "comments": [
            {
               "date": "30 January 2022 06:14",
               "html": "<p>I find this paragraph vague, too.</p>\n",
               "id": "988",
               "name": " Jakub",
               "pub": "2022-01-30T18:14:29",
               "ref": "982",
               "type": "comment"
            },
            {
               "date": "31 January 2022 08:12",
               "html": "<p>You&#39;re right -- I remember figuring that out during the RIPE presentation. Maybe it was handled during the questions, will write a follow-up blog post.</p>\n",
               "id": "989",
               "name": "Ivan Pepelnjak",
               "pub": "2022-01-31T08:12:11",
               "ref": "982",
               "type": "comment"
            }
         ],
         "date": "26 January 2022 10:05",
         "html": "<p>What do you mean by &quot;serious ARP glue&quot;? I found no clue about that in your referenced RIPE presentation.</p>\n",
         "id": "982",
         "name": "Anonymous",
         "pub": "2022-01-26T22:05:41",
         "type": "comment"
      },
      {
         "date": "05 February 2022 02:34",
         "html": "<p>Hi,</p>\n\n<p>are you aware of any BGP over CLNS implementation?</p>\n\n<h2 id=\"thankyou\">thank you</h2>\n\n<p>antonio</p>\n",
         "id": "1000",
         "name": " Antonio Prado",
         "pub": "2022-02-05T14:34:51",
         "type": "comment"
      }
   ],
   "count": 2,
   "type": "post",
   "url": "2022/01/bgp-af-nerd-knobs.html"
}
