{
   "comments": [
      {
         "date": "14 April 2021 10:21",
         "html": "<p>We are doing similar automation based on Netconf-Yang (for nx-os, juniper and arista) since 2017 (or we use GNMI-Yang for SONiC) \nThe controller is a trimmed down opendaylight distribution.</p>\n\n<p>The approach is similar to this, but it&#39;s all rest driver from a UI to backend.</p>\n\n<p>I wish i could share more details :( but it&#39;s proprietary code.\nIf you have contacts in AT&amp;T ask for SDDC (Software Defined DC)</p>\n",
         "id": "516",
         "name": "Andrea Florio",
         "pub": "2021-04-14T10:21:57",
         "type": "comment"
      }
   ],
   "count": 1,
   "type": "post",
   "url": "2021/04/automate-nxos-fabric-deployment.html"
}
