{
   "comments": [
      {
         "date": "18 January 2021 11:23",
         "html": "<p>Very interesting Ivan !! </p>\n\n<p>Looks like Nokia too uses the Routing table&#39;s prefix&#39;s Admin-distance/Preference as a very early BGP tie-breaker. \nCheck this out @ entry#3: https://infocenter.nokia.com/public/7750SR151R1A/topic/com.sr.unicast/html/bgp.html?cp=19_4_6_1_0#addamr5ieywiaklnc  </p>\n\n<p>Cheers/Ciao <br />\nAndrea    </p>\n",
         "id": "347",
         "name": " andrea di donato",
         "pub": "2021-01-18T11:23:47",
         "type": "comment"
      }
   ],
   "count": 1,
   "type": "post",
   "url": "2021/01/bgp-igp-metric-admin-distance.html"
}
