{
  "comments": [
    {
      "date": "08 November 2007 04:04",
      "html": "Hi there,<BR/><BR/>I telnet to the router with local authentication and the username doesn't get displayed for some reason. Any idea why?<BR/><BR/>Thankyou!<BR/><BR/><BR/><BR/>      RTR001-03<BR/>      2007-11-08 13:36:36 Router_1 192.168.1.1 -  Login Success [user: ] [Source: 192.168.1.2] [localport: 23] at 13:31:12 AEDT Thu Nov 8 2007",
      "id": "2301837964054687522",
      "image": "https://lh3.googleusercontent.com/zFdxGE77vvD2w5xHy6jkVuElKv-U9_9qLkRYK8OnbDeJPtjSZ82UPq5w6hJ-SA=s35",
      "name": "Unknown",
      "profile": "https://www.blogger.com/profile/07316278732082733254",
      "pub": "2007-11-08T04:04:00.000+01:00",
      "ref": "116508876101347377",
      "type": "comment"
    },
    {
      "date": "18 November 2007 13:57",
      "html": "Hi Peter!<BR/><BR/>I've just re-tested this feature with non-AAA and AAA local authentication in IOS release 12.4(15)T1. It reported the username in both cases, so you're probably hitting a bug.",
      "id": "2789498356049353890",
      "image": "https://lh3.googleusercontent.com/zFdxGE77vvD2w5xHy6jkVuElKv-U9_9qLkRYK8OnbDeJPtjSZ82UPq5w6hJ-SA=s35",
      "name": "Ivan Pepelnjak",
      "profile": "https://www.blogger.com/profile/13457151406311272386",
      "pub": "2007-11-18T13:57:00.000+01:00",
      "ref": "116508876101347377",
      "type": "comment"
    },
    {
      "date": "04 February 2011 17:22",
      "html": "I get the same thing no userid displayed",
      "id": "1008876758574406554",
      "image": "https://resources.blogblog.com/img/blank.gif",
      "name": "plnnightsky",
      "profile": null,
      "pub": "2011-02-04T17:22:06.000+01:00",
      "ref": "116508876101347377",
      "type": "comment"
    },
    {
      "date": "04 February 2011 20:23",
      "html": "Yes it is a bug <br />http://tools.cisco.com/Support/BugToolKit/search/getBugDetails.do?method=fetchBugDetails&amp;bugId=CSCsm55629",
      "id": "4535752070960785117",
      "image": "https://resources.blogblog.com/img/blank.gif",
      "name": "plnnightsky",
      "profile": null,
      "pub": "2011-02-04T20:23:38.000+01:00",
      "ref": "116508876101347377",
      "type": "comment"
    }
  ],
  "count": 4,
  "id": "116508876101347377",
  "type": "post",
  "url": "2006/12/log-terminal-access-to-your-router.html"
}