[
  {
    "title": "How Moving Away from Ansible Made netlab Faster",
    "url": "/2026/01/netlab-faster-without-ansible/"
  },
  {
    "title": "Opinion: Impact of AI on Networking Engineers",
    "url": "/2026/01/ai-impact-networking-engineers/"
  },
  {
    "title": "Has Ansible Team Abandoned Network Automation?",
    "url": "/2025/12/ansible-abandoned-network-automation/"
  },
  {
    "title": "OMG, After a Decade, VXLAN Is Still Insecure",
    "url": "/2026/02/worth-reading-omg-vxlan-still-insecure/"
  },
  {
    "title": "Do You Need IS-IS Areas?",
    "url": "/2026/01/is-is-areas/"
  },
  {
    "title": "Lab: VXLAN Bridging with EVPN Control Plane",
    "url": "/2026/01/lab-evpn-bridging/"
  },
  {
    "title": "Technology Resources",
    "url": "/series/"
  },
  {
    "title": "On MPLS Paths, Tunnels and Interfaces",
    "url": "/2026/01/mpls-paths-tunnels-interfaces/"
  },
  {
    "title": "Fast FRR Container Configuration",
    "url": "/2026/02/netlab-frr-configuration/"
  },
  {
    "title": "Public Videos: Network Observability",
    "url": "/2026/01/video-network-observability/"
  },
  {
    "title": "Interface MAC Address in IOS Layer-2 Images",
    "url": "/2026/02/ios-layer2-mac-address/"
  },
  {
    "title": "Infrahub with Damien Garros",
    "url": "/2026/01/infrahub-damien-garros/"
  },
  {
    "title": "Build Virtual Labs with netlab",
    "url": "/tag/netlab/"
  },
  {
    "title": "MUST READ: Machine Learning for Network and Cloud Engineers",
    "url": "/2023/02/machine-learning-network-cloud/"
  },
  {
    "title": "netlab 26.01: EVPN for VXLAN-over-IPv6, Netscaler",
    "url": "/2026/01/netlab-26-01/"
  },
  {
    "title": "Why Doesn't netlab Use X for Device Configuration Templates?",
    "url": "/2026/01/netlab-not-using-vendor-templates/"
  },
  {
    "title": "Lab: Distributing Level-2 IS-IS Routes into Level-1 Areas",
    "url": "/2026/01/isis-inter-area-routes/"
  },
  {
    "title": "MUST WATCH: BGP: the First 18 Years",
    "url": "/2026/01/worth-reading-bgp-first-18-years/"
  },
  {
    "title": "Multiline Expressions in Ansible Playbooks",
    "url": "/2024/03/ansible-multiline-expressions/"
  },
  {
    "title": "On MPLS Forwarding Performance Myths",
    "url": "/2026/02/mpls-forwarding-performance/"
  },
  {
    "title": "BGP, EVPN, VXLAN, or SRv6?",
    "url": "/2024/07/bgp-evpn-vxlan-srv6/"
  },
  {
    "title": "Lab: More Complex VXLAN Deployment Scenario",
    "url": "/2025/12/vxlan-complex/"
  },
  {
    "title": "Worth Reading: A Tech Career in 2026",
    "url": "/2026/01/worth-reading-tech-career-2026/"
  },
  {
    "title": "EVPN Designs: VXLAN Leaf-and-Spine Fabric",
    "url": "/2024/04/evpn-designs-vxlan-leaf-spine-fabric/"
  },
  {
    "title": "TCP MSS Clamping \u2013 What Is It and Why Do We Need It?",
    "url": "/2013/01/tcp-mss-clamping-what-is-it-and-why-do/"
  },
  {
    "title": "VLANs and Failure Domains Revisited",
    "url": "/2016/02/vlans-and-failure-domains-revisited/"
  },
  {
    "title": "BGP Graceful Restart Considered Harmful",
    "url": "/2024/01/bgp-graceful-restart-harmful/"
  },
  {
    "title": "Cumulus Linux (As We Know It) Is Gone",
    "url": "/2025/06/cumulus-linux-gone/"
  },
  {
    "title": "Fundamentals: Is Switching Latency Relevant?",
    "url": "/2021/04/switching-latency-relevant/"
  },
  {
    "title": "Using netlab to Set Up Demos",
    "url": "/2026/01/using-netlab-demos/"
  },
  {
    "title": "Running netlab and BGP Labs on Apple Silicon",
    "url": "/2024/03/netlab-bgp-apple-silicon/"
  },
  {
    "title": "Mixed Feelings about BGP Route Reflector Cluster ID",
    "url": "/2022/02/bgp-rr-cluster-myths/"
  },
  {
    "title": "Ansible Release 12: the Windows Vista Moment",
    "url": "/2025/11/ansible-12-different/"
  },
  {
    "title": "Deploy Partially-Configured Training Labs with netlab",
    "url": "/2026/01/netlab-partial-configuration/"
  },
  {
    "title": "ipSpace.net blog",
    "url": "/page/2/"
  },
  {
    "title": "Management, Control, and Data Planes in Network Devices and Systems",
    "url": "/2013/08/management-control-and-data-planes-in/"
  },
  {
    "title": "CI/CD in Networking",
    "url": "/series/cicd/"
  },
  {
    "title": "OMG, VXLAN Is Still Insecure",
    "url": "/2018/11/omg-vxlan-is-still-insecure/"
  },
  {
    "title": "\u00ab ipSpace.net blog",
    "url": "/2026/01/"
  },
  {
    "title": "ARP Challenges in EVPN/VXLAN Symmetric IRB",
    "url": "/2025/04/evpn-symmetric-irb-arp/"
  },
  {
    "title": "Implicit and Explicit Null Label in MPLS networks",
    "url": "/kb/tag/MPLS/Implicit_Explicit_NULL/"
  },
  {
    "title": "BGP AS-Path Prepending: Technical Details",
    "url": "/2009/03/as-path-prepending-technical-details/"
  },
  {
    "title": "RIBs and FIBs (aka IP Routing Table and CEF Table)",
    "url": "/2010/09/ribs-and-fibs/"
  },
  {
    "title": "Android Phones Might Ask for /64 Delegated Prefix",
    "url": "/2025/09/android-dhcpv6-prefix-delegation/"
  },
  {
    "title": "Docker Userland Proxy",
    "url": "/kb/DockerSvc/40-userland-proxy/"
  },
  {
    "title": "DHCP conflict logging: the true story",
    "url": "/2007/08/dhcp-conflict-logging-true-story/"
  },
  {
    "title": "Can I Use Shared (RFC 6598) IPv4 Address Space Within My Network?",
    "url": "/2013/08/can-i-use-shared-rfc-6598-ipv4-address/"
  }
]