{
   "comments": [
      {
         "date": "17 September 2020 12:43",
         "html": "<p>&gt; Amazon has a real need for smart NICs to support bare-metal server instances</p>\n\n<p>According to teh Internets, Nitro predates .metal instances by ~4 years, having been launched in 2013 to support the C3 instance types.</p>\n\n<p>Apart from the hardware offload/acceleration, there&#39;s real value in having an ability to handle network security policy enforcement outside of the VM OS or a hypervisor.</p>\n",
         "id": "137",
         "name": " Dmitri Kalintsev",
         "pub": "2020-09-17T12:43:33",
         "type": "comment"
      }
   ],
   "count": 1,
   "type": "post",
   "url": "2020/09/business-needs-excuses.html"
}
